<?xml version="1.0" encoding="UTF-8"?>
<AppConfig>
	<!-- Database type values: SqlServer2008, Oracle -->
	<Database type="SqlServer2008" >
		<ConnectionString name="Baseline" environment="Staging" value="jdbc:sqlserver://localhost:1433;databaseName=DB_BASELINE;user=sa;password=marius123" />		
		<ConnectionString name="Target" environment="Testing" value="jdbc:sqlserver://localhost:1433;databaseName=DB_TARGET;user=sa;password=marius123" />
	</Database>
	<!-- Report type: SideBySide, Inline, Both -->
	<Report type="SideBySide" directory="ComparisonReport" />	 
	<Table name="TBDEMO">
		<PrimaryKeyColumn name="ID" />
		<Column name="NAME" />
		<Column name="DESCRIPTION" />	
		<Column name="QUANTITY" />
		<Column name="TEXT" />
	</Table>
</AppConfig>